odoo/addons/test_base_duration/README.rst
odoo/addons/test_base_duration/__init__.py
odoo/addons/test_base_duration/__manifest__.py
odoo/addons/test_base_duration/models/__init__.py
odoo/addons/test_base_duration/models/test_base_duration.py
odoo/addons/test_base_duration/security/ir.model.access.csv
odoo/addons/test_base_duration/static/description/icon.png
odoo/addons/test_base_duration/views/test_base_duration_views.xml
odoo14_addon_test_base_duration-14.0.1.0.2.dist-info/METADATA
odoo14_addon_test_base_duration-14.0.1.0.2.dist-info/WHEEL
odoo14_addon_test_base_duration-14.0.1.0.2.dist-info/top_level.txt
odoo14_addon_test_base_duration-14.0.1.0.2.dist-info/RECORD
